airflow_provider_olostep/__init__.py
airflow_provider_olostep/example_dags/__init__.py
airflow_provider_olostep/example_dags/example_ecommerce_monitor.py
airflow_provider_olostep/example_dags/example_quickstart.py
airflow_provider_olostep/hooks/__init__.py
airflow_provider_olostep/hooks/olostep.py
airflow_provider_olostep/operators/__init__.py
airflow_provider_olostep/operators/answer.py
airflow_provider_olostep/operators/batch.py
airflow_provider_olostep/operators/crawl.py
airflow_provider_olostep/operators/map.py
airflow_provider_olostep/operators/scrape.py
airflow_provider_olostep/sensors/__init__.py
airflow_provider_olostep/sensors/batch.py
airflow_provider_olostep/sensors/crawl.py
apache_airflow_provider_olostep-0.2.0.dist-info/METADATA
apache_airflow_provider_olostep-0.2.0.dist-info/WHEEL
apache_airflow_provider_olostep-0.2.0.dist-info/entry_points.txt
apache_airflow_provider_olostep-0.2.0.dist-info/top_level.txt
apache_airflow_provider_olostep-0.2.0.dist-info/RECORD
