Metadata-Version: 2.4
Name: apache-airflow-provider-olostep
Version: 0.2.0
Summary: Apache Airflow provider for Olostep web scraping API
Author-email: Olostep <info@olostep.com>
License: Apache-2.0
Project-URL: Homepage, https://olostep.com
Project-URL: Documentation, https://docs.olostep.com/integrations/airflow
Project-URL: Repository, https://github.com/olostep/airflow-provider-olostep
Project-URL: Changelog, https://github.com/olostep/airflow-provider-olostep/blob/main/CHANGELOG.md
Project-URL: Bug Tracker, https://github.com/olostep/airflow-provider-olostep/issues
Keywords: airflow,olostep,web-scraping,data-extraction,provider,etl,data-pipeline
Classifier: Development Status :: 4 - Beta
Classifier: Environment :: Console
Classifier: Framework :: Apache Airflow
Classifier: Framework :: Apache Airflow :: Provider
Classifier: Intended Audience :: Developers
Classifier: Intended Audience :: System Administrators
Classifier: License :: OSI Approved :: Apache Software License
Classifier: Operating System :: OS Independent
Classifier: Programming Language :: Python :: 3
Classifier: Programming Language :: Python :: 3.8
Classifier: Programming Language :: Python :: 3.9
Classifier: Programming Language :: Python :: 3.10
Classifier: Programming Language :: Python :: 3.11
Classifier: Programming Language :: Python :: 3.12
Classifier: Topic :: Internet :: WWW/HTTP
Classifier: Topic :: System :: Monitoring
Requires-Python: >=3.8
Requires-Dist: apache-airflow>=2.4.0
Requires-Dist: requests>=2.25.0
Provides-Extra: dev
Requires-Dist: pytest>=7.0.0; extra == "dev"
Requires-Dist: pytest-mock>=3.10.0; extra == "dev"
Requires-Dist: pytest-asyncio>=0.21.0; extra == "dev"
Requires-Dist: responses>=0.22.0; extra == "dev"
Requires-Dist: apache-airflow[testing]>=2.4.0; extra == "dev"
